repligit/__init__.py
repligit/client.py
repligit/parse.py
repligit/asyncio/__init__.py
repligit/asyncio/client.py
repligit/asyncio/parse.py
repligit-0.2.0.dist-info/METADATA
repligit-0.2.0.dist-info/WHEEL
repligit-0.2.0.dist-info/licenses/LICENSE
repligit-0.2.0.dist-info/RECORD
