Metadata-Version: 2.4
Name: repligit
Version: 0.2.0
Summary: A python library implementing the git http transfer protocol.
Project-URL: Homepage, https://github.com/llnl/repligit
Project-URL: Issues, https://github.com/llnl/repligit/issues
Author: Alec Scott, Caetano Melone
License-Expression: Apache-2.0 WITH LLVM-exception
License-File: LICENSE
Classifier: Operating System :: OS Independent
Classifier: Programming Language :: Python :: 3
Requires-Python: >=3.10
Provides-Extra: aiohttp
Requires-Dist: aiohttp; extra == 'aiohttp'
